sqlmesh/__init__.py
sqlmesh/_version.py
sqlmesh/magics.py
sqlmesh/py.typed
sqlmesh/cicd/__init__.py
sqlmesh/cicd/bot.py
sqlmesh/cicd/config.py
sqlmesh/cli/__init__.py
sqlmesh/cli/example_project.py
sqlmesh/cli/main.py
sqlmesh/cli/options.py
sqlmesh/core/__init__.py
sqlmesh/core/_typing.py
sqlmesh/core/console.py
sqlmesh/core/constants.py
sqlmesh/core/context.py
sqlmesh/core/context_diff.py
sqlmesh/core/cube.py
sqlmesh/core/dialect.py
sqlmesh/core/environment.py
sqlmesh/core/lineage.py
sqlmesh/core/loader.py
sqlmesh/core/macros.py
sqlmesh/core/node.py
sqlmesh/core/notification_target.py
sqlmesh/core/openai_client.py
sqlmesh/core/reference.py
sqlmesh/core/renderer.py
sqlmesh/core/scheduler.py
sqlmesh/core/schema_diff.py
sqlmesh/core/schema_loader.py
sqlmesh/core/selector.py
sqlmesh/core/signal.py
sqlmesh/core/table_diff.py
sqlmesh/core/user.py
sqlmesh/core/analytics/__init__.py
sqlmesh/core/analytics/collector.py
sqlmesh/core/analytics/dispatcher.py
sqlmesh/core/audit/__init__.py
sqlmesh/core/audit/builtin.py
sqlmesh/core/audit/definition.py
sqlmesh/core/config/__init__.py
sqlmesh/core/config/base.py
sqlmesh/core/config/categorizer.py
sqlmesh/core/config/common.py
sqlmesh/core/config/connection.py
sqlmesh/core/config/feature_flag.py
sqlmesh/core/config/format.py
sqlmesh/core/config/gateway.py
sqlmesh/core/config/loader.py
sqlmesh/core/config/migration.py
sqlmesh/core/config/model.py
sqlmesh/core/config/naming.py
sqlmesh/core/config/plan.py
sqlmesh/core/config/root.py
sqlmesh/core/config/run.py
sqlmesh/core/config/scheduler.py
sqlmesh/core/config/ui.py
sqlmesh/core/engine_adapter/__init__.py
sqlmesh/core/engine_adapter/_typing.py
sqlmesh/core/engine_adapter/athena.py
sqlmesh/core/engine_adapter/base.py
sqlmesh/core/engine_adapter/base_postgres.py
sqlmesh/core/engine_adapter/bigquery.py
sqlmesh/core/engine_adapter/clickhouse.py
sqlmesh/core/engine_adapter/databricks.py
sqlmesh/core/engine_adapter/duckdb.py
sqlmesh/core/engine_adapter/mixins.py
sqlmesh_cube-0.1.dev3089.dist-info/LICENSE
sqlmesh_cube-0.1.dev3089.dist-info/METADATA
sqlmesh_cube-0.1.dev3089.dist-info/WHEEL
sqlmesh_cube-0.1.dev3089.dist-info/entry_points.txt
sqlmesh_cube-0.1.dev3089.dist-info/top_level.txt
sqlmesh_cube-0.1.dev3089.dist-info/RECORD
